{
  "schema_version": "0.1.0",
  "work_item_id": "wi_260715clv",
  "seq": 2,
  "actor": "workspace-write",
  "event_id": "a809ac77f03c24de1bbd9ed2cb567b4e08902b834e76c06b317abab0b7280326",
  "ts": "2026-07-15T04:59:44.685Z",
  "kind": "verdict",
  "payload": {
    "criterion_id": "ac-1",
    "verdict": "pass",
    "evidence": [
      {
        "kind": "command",
        "command": "bash -c grep -q \"자연스러운 한국어로 쓴다. 영어를 단어 단위로 옮긴 직역체\" AGENTS.md && echo AC1_PRESENT",
        "summary": "exit 0"
      }
    ]
  }
}
