{
  "schema_version": "0.1.0",
  "id": "wi_260605dg2",
  "title": "Assurance drift 소비처 — rising 추세 게이트(ditto fitness drift --gate)",
  "source_request": "ACG 남은 작업 C2: drift 시계열 소비처(추세 차단). C1(스케줄러)은 CI/harness 몫이라 제외.",
  "goal": "drift 뷰(computeDrift)를 행동으로 연결한다. rising 추세이면서 누적 신규위반이 임계 이상인 function을 '주의'로 판정하고, ditto fitness drift --gate가 그런 function이 있으면 exit 1로 종료해 CI가 SLOP 가속에 빌드를 실패시킬 수 있게 한다. C1(주기 스케줄러)은 CI cron 몫이라 범위 밖.",
  "acceptance_criteria": [
    {
      "id": "ac-1",
      "statement": "순수 assessDrift(report, minNewViolations=0) → {concerning: rising && cumulative_new_violations>=임계, reasons}. 단위테스트(rising만·임계 필터·빈).",
      "verdict": "pass",
      "evidence": [
        { "kind": "file", "summary": "src/acg/fitness/drift.ts: assessDrift — direction==='rising' && cumulative_new_violations>=minNewViolations인 function을 concerning으로, reasons 생성." },
        { "kind": "command", "summary": "bun test fitness-drift.test.ts: rising만 concerning(falling/flat 제외), min_new_violations 임계 필터(누적 4: 4>=4 통과·4>=5 제외), 빈 리포트 (3 pass)." }
      ]
    },
    {
      "id": "ac-2",
      "statement": "ditto fitness drift --gate [--min-new-violations N]: 뷰 렌더 후 concerning 있으면 exit 1(없으면/--gate 미지정이면 0). json은 gate 결과 포함. 합성 스냅샷 e2e.",
      "verdict": "pass",
      "evidence": [
        { "kind": "file", "summary": "src/cli/commands/fitness.ts: drift --gate/--min-new-violations 배선. 게이트 시 GATE 블록 출력·json에 gate{concerning,min_new_violations}·concerning>0이면 process.exit(RUNTIME_ERROR_EXIT)." },
        { "kind": "command", "summary": "e2e(rising ff-dup 1→4, +4 new): --gate 없으면 exit 0, --gate면 GATE 블록+exit 1, --gate --min-new-violations 5(4<5)면 exit 0, json gate={concerning:['ff-dup'],min_new_violations:0}." }
      ]
    },
    {
      "id": "ac-3",
      "statement": "전체 bun test·lint·build green. 기존 fitness drift(게이트 미지정)·run 무회귀.",
      "verdict": "pass",
      "evidence": [
        { "kind": "command", "summary": "bun test 전체 1123 pass/3 skip/0 fail(+3), biome clean, build clean. --gate 미지정 시 drift 출력·exit 0 무변경." }
      ]
    }
  ],
  "status": "done",
  "owner_profile": "workspace-write",
  "child_ids": [],
  "changed_files": ["src/acg/fitness/drift.ts", "src/cli/commands/fitness.ts", "tests/acg/fitness-drift.test.ts"],
  "risks": [],
  "runs": [],
  "created_at": "2026-06-05T08:35:00.000Z",
  "updated_at": "2026-06-05T08:45:00.000Z",
  "closed_at": "2026-06-05T08:45:00.000Z"
}
